deploykit/LICENSE
deploykit/ThirdPartyNotices.txt
deploykit/__init__.py
deploykit/deploykit_cpp2py_export.cpython-39-x86_64-linux-gnu.so
deploykit/version.py
deploykit-0.0.1a1.dist-info/LICENSE
deploykit-0.0.1a1.dist-info/METADATA
deploykit-0.0.1a1.dist-info/WHEEL
deploykit-0.0.1a1.dist-info/top_level.txt
deploykit-0.0.1a1.dist-info/RECORD
deploykit.libs/libonnxruntime-9bf6e2a0.so.1.11.1
deploykit.libs/libdeploykit-172ffe4d.so
deploykit.libs/libpaddle2onnx-ede372e5.so
