Metadata-Version: 2.1
Name: deploykit
Version: 0.0.1a1
Summary: Deploy Kit Tool For Deeplearning models.
Home-page: https://github.com/PaddlePaddle/Paddle2ONNX.git
Author: paddle-infer
Author-email: paddle-infer@baidu.com
License: Apache 2.0
Platform: UNKNOWN
Classifier: Programming Language :: Python :: 3
Classifier: License :: OSI Approved :: Apache Software License
Classifier: Operating System :: OS Independent
License-File: LICENSE
Provides-Extra: mypy
Requires-Dist: mypy (==0.600) ; extra == 'mypy'
